{
  "project_info": {
    "project_number": "64557969018",
    "project_id": "chatapp-18ea6",
    "storage_bucket": "chatapp-18ea6.appspot.com"
  },
  "client": [
    {
      "client_info": {
        "mobilesdk_app_id": "1:64557969018:android:ee7ef2c379fc0439d495c3",
        "android_client_info": {
          "package_name": "com.example.chatapp"
        }
      },
      "oauth_client": [
        {
          "client_id": "64557969018-5k46f2o5fkkep3m5nndmqo4610467ppj.apps.googleusercontent.com",
          "client_type": 3
        }
      ],
      "api_key": [
        {
          "current_key": "AIzaSyCAHk1KAst3QORgoN7EUk4zg4T3XdIyuV0"
        }
      ],
      "services": {
        "appinvite_service": {
          "other_platform_oauth_client": [
            {
              "client_id": "64557969018-5k46f2o5fkkep3m5nndmqo4610467ppj.apps.googleusercontent.com",
              "client_type": 3
            }
          ]
        }
      }
    }
  ],
  "configuration_version": "1"
}